jdtree/__init__.py
jdtree/condition.py
jdtree/constants.py
jdtree/jdt_engine.py
jdtree-0.0.5.dist-info/LICENSE
jdtree-0.0.5.dist-info/METADATA
jdtree-0.0.5.dist-info/WHEEL
jdtree-0.0.5.dist-info/top_level.txt
jdtree-0.0.5.dist-info/RECORD
