Metadata-Version: 2.1
Name: jdtree
Version: 0.0.5
Summary: Json Decision Table/Tree
Author: Matteo Greco
License: MIT
License-File: LICENSE
